[
    {
        "name": "Mateusz Rorat",
        "birth": "2019"
    },
    {
        "name": "Celina Gierczak",
        "birth": "2019"
    },
    {
        "name": "Papet",
        "birth": "2018"
    },
    {
        "name": "Tori",
        "birth": "2012"
    },
    {
        "name": "aaa",
        "birth": "2012"
    },
    {
        "name": "punia",
        "birth": "2004"
    },
    {
        "name": "Kajtek",
        "birth": "2004"
    },
    {
        "name": "Tori",
        "birth": "2004"
    },
    {
        "name": "Kajtek",
        "birth": "2004"
    },
    {
        "name": "punia",
        "birth": "2004"
    },
    {
        "name": "Kajtek",
        "birth": "2009"
    },
    {
        "name": "Kajtek",
        "birth": "2012"
    },
    {
        "name": "Tori",
        "birth": "2004"
    },
    {
        "name": "Kajtek",
        "birth": "2004"
    },
    {
        "name": "Tori",
        "birth": "2012"
    },
    {
        "name": "Fzia",
        "birth": "2004"
    },
    {
        "name": "punia",
        "birth": "unknown"
    },
    {
        "name": "Kajtek",
        "birth": "2002"
    },
    {
        "name": "Boni",
        "birth": "2001"
    },
    {
        "name": "Fzia",
        "birth": "2012"
    },
    {
        "name": "Boni",
        "birth": "2001"
    },
    {
        "name": "Boni",
        "birth": "2001"
    },
    {
        "name": "Boni",
        "birth": "2001"
    },
    {
        "name": "Boni",
        "birth": "2001"
    },
    {
        "name": "Boni",
        "birth": "2001"
    },
    {
        "name": "Tori",
        "birth": "2012"
    },
    {
        "name": "Kajtek",
        "birth": "2012"
    },
    {
        "name": "Kajtek",
        "birth": "2002"
    },
    {
        "name": "Tori",
        "birth": "2004"
    },
    {
        "name": "Amelia",
        "birth": "2015"
    },
    {
        "name": "Papet",
        "birth": "2018"
    },
    {
        "name": "Punia",
        "birth": "2004"
    },
    {
        "name": "Fzia",
        "birth": "2012"
    },
    {
        "name": "Kajtek",
        "birth": "2008"
    },
    {
        "name": "Kajtek",
        "birth": "2008"
    },
    {
        "name": "Tori",
        "birth": "2002"
    },
    {
        "name": "Tori",
        "birth": "2002"
    },
    {
        "name": "Kajtek",
        "birth": "2010"
    },
    {
        "name": "Kajtek",
        "birth": "2010"
    },
    {
        "name": "Misiek",
        "birth": "2012"
    },
    {
        "name": "Tori",
        "birth": "2004"
    },
    {
        "name": "Fzia",
        "birth": "2012"
    }
]